video_mcp_server.py
video_tools_mcp-0.1.2.dist-info/METADATA
video_tools_mcp-0.1.2.dist-info/WHEEL
video_tools_mcp-0.1.2.dist-info/entry_points.txt
video_tools_mcp-0.1.2.dist-info/licenses/LICENSE
video_tools_mcp-0.1.2.dist-info/RECORD
