Metadata-Version: 2.4
Name: video-tools-mcp
Version: 0.1.2
Summary: MCP Server for video processing - extract frames, metadata, audio and create GIFs
Project-URL: Homepage, https://github.com/TiGRoNdev/video-tools-mcp
Project-URL: Repository, https://github.com/TiGRoNdev/video-tools-mcp
Project-URL: Documentation, https://github.com/TiGRoNdev/video-tools-mcp#readme
Project-URL: Bug Tracker, https://github.com/TiGRoNdev/video-tools-mcp/issues
Author-email: TiGRoN <tigron.dev@gmail.com>
License: MIT
License-File: LICENSE
Keywords: audio,ffmpeg,frames,gif,mcp,model-context-protocol,video
Classifier: Development Status :: 4 - Beta
Classifier: Intended Audience :: Developers
Classifier: License :: OSI Approved :: MIT License
Classifier: Programming Language :: Python :: 3
Classifier: Programming Language :: Python :: 3.10
Classifier: Programming Language :: Python :: 3.11
Classifier: Programming Language :: Python :: 3.12
Classifier: Topic :: Multimedia :: Video
Classifier: Topic :: Software Development :: Libraries :: Python Modules
Requires-Python: >=3.10
Requires-Dist: mcp>=1.0.0
Provides-Extra: dev
Requires-Dist: black>=23.0.0; extra == 'dev'
Requires-Dist: pytest-asyncio>=0.21.0; extra == 'dev'
Requires-Dist: pytest-cov>=4.0.0; extra == 'dev'
Requires-Dist: pytest>=7.0.0; extra == 'dev'
Requires-Dist: ruff>=0.1.0; extra == 'dev'
